geopathfinder/__init__.py
geopathfinder/file_naming.py
geopathfinder/folder_naming.py
geopathfinder/naming_conventions/acube_naming.py
geopathfinder/naming_conventions/bmon_naming.py
geopathfinder/naming_conventions/eodr_naming.py
geopathfinder/naming_conventions/sgrt_naming.py
geopathfinder/naming_conventions/yeoda_naming.py
geopathfinder-0.2.0.dist-info/licenses/LICENSE.txt
geopathfinder-0.2.0.dist-info/METADATA
geopathfinder-0.2.0.dist-info/WHEEL
geopathfinder-0.2.0.dist-info/top_level.txt
geopathfinder-0.2.0.dist-info/RECORD
