Metadata-Version: 2.4
Name: geopathfinder
Version: 0.2.0
Summary: Creating, quering, and searching in data structures holding geo-datasets.
Home-page: https://github.com/TUW-GEO/geopathfinder
Author: TU Wien
Author-email: remote.sensing@geo.tuwien.ac.at
License: MIT
Project-URL: Documentation, https://geopathfinder.readthedocs.io/
Platform: any
Classifier: Development Status :: 4 - Beta
Classifier: Programming Language :: Python
License-File: LICENSE.txt
Requires-Dist: importlib-metadata; python_version < "3.8"
Requires-Dist: numpy
Requires-Dist: pandas
Requires-Dist: python_dateutil
Requires-Dist: pytz
Requires-Dist: regex
Provides-Extra: testing
Requires-Dist: setuptools; extra == "testing"
Requires-Dist: pytest; extra == "testing"
Requires-Dist: pytest-cov; extra == "testing"
Dynamic: license-file
